[
  {
    "id": "20250519-F325-001",
    "title": "This is a new one",
    "description": "this is new",
    "long_description": "this is more new",
    "event_date": "2025-05-20",
    "display_from_date": "2025-05-19",
    "tags": [
      "sonar",
      "beefy"
    ],
    "group_id": "g1",
    "full_image_url": "https://sonar-media.sfo3.digitaloceanspaces.com/images/20250519-F325-001-full.png",
    "small_image_url": "https://sonar-media.sfo3.digitaloceanspaces.com/images/20250519-F325-001-small.png",
    "thumb_image_url": "https://sonar-media.sfo3.digitaloceanspaces.com/images/20250519-F325-001-thumb.png",
    "images_uploaded_to_s3": true,
    "event_updated_not_submitted": false,
    "ticket_url": ""
  },
  {
    "id": "20250520-F325-001",
    "title": "test event",
    "description": "dest tescription",
    "long_description": "heres a long one",
    "event_date": "2025-05-24",
    "display_from_date": "2025-05-20",
    "tags": [
      "sonar",
      "test",
      "me",
      "you"
    ],
    "full_image_url": "https://sonar-media.sfo3.digitaloceanspaces.com/images/20250520-F325-001-full.png",
    "small_image_url": "https://sonar-media.sfo3.digitaloceanspaces.com/images/20250520-F325-001-small.png",
    "thumb_image_url": "https://sonar-media.sfo3.digitaloceanspaces.com/images/20250520-F325-001-thumb.png",
    "group_id": "g1",
    "images_uploaded_to_s3": true,
    "event_updated_not_submitted": false,
    "ticket_url": ""
  },
  {
    "id": "20250611-70A3-002",
    "title": "Chamber Music Party (7/12 2-5pm)",
    "description": "Members of the Tempe Symphony - Summer Chamber Music Soiree",
    "long_description": "If you're with the Tempe Symphony RSVP to the eventbrite and come have a great time! Park in whatever spots you find.  Enter through the side door - hopefully we'll have a sign :-)",
    "event_date": "2025-07-12T17:00",
    "display_from_date": "2025-06-11T17:00",
    "tags": [
      "sonar",
      "rlc"
    ],
    "ticket_url": "",
    "full_image_url": "https://sonar-media.sfo3.digitaloceanspaces.com/images/20250611-70A3-001-full.png",
    "small_image_url": "https://sonar-media.sfo3.digitaloceanspaces.com/images/20250611-70A3-001-small.png",
    "thumb_image_url": "https://sonar-media.sfo3.digitaloceanspaces.com/images/20250611-70A3-001-thumb.png",
    "group_id": "g1",
    "images_uploaded_to_s3": true,
    "event_updated_not_submitted": false
  },
  {
    "id": "20250704-B835-001",
    "title": "Chamber Music Party (7/13 2-5pm)",
    "description": "Members of the Tempe Symphony - Summer Chamber Music Soiree",
    "long_description": "If you're with the Tempe Symphony RSVP to the eventbrite and come have a great time! Park in whatever spots you find.  Enter through the side door - hopefully we'll have a sign :-)",
    "event_date": "2025-07-13T19:00",
    "display_from_date": "2025-06-11T20:00",
    "tags": [
      "sonar",
      "rlc",
      "signal-9"
    ],
    "ticket_url": "https://example.com/tickets",
    "full_image_url": "https://sonar-media.sfo3.digitaloceanspaces.com/images/20250611-70A3-001-full.png",
    "small_image_url": "https://sonar-media.sfo3.digitaloceanspaces.com/images/20250611-70A3-001-small.png",
    "thumb_image_url": "https://sonar-media.sfo3.digitaloceanspaces.com/images/20250611-70A3-001-thumb.png",
    "group_id": "g1",
    "images_uploaded_to_s3": true,
    "event_updated_not_submitted": false
  },
  {
    "id": "20250519-F325-004",
    "title": "New Event 4",
    "description": "New Event",
    "long_description": "New Event here",
    "event_date": "2025-05-21",
    "display_from_date": "2025-05-19",
    "tags": [
      "sonar",
      "this",
      "that"
    ],
    "full_image_url": "https://sonar-media.sfo3.digitaloceanspaces.com/images/20250519-F325-004-full.png",
    "small_image_url": "https://sonar-media.sfo3.digitaloceanspaces.com/images/20250519-F325-004-small.png",
    "thumb_image_url": "https://sonar-media.sfo3.digitaloceanspaces.com/images/20250519-F325-004-thumb.png",
    "group_id": "g1",
    "images_uploaded_to_s3": true,
    "event_updated_not_submitted": false,
    "ticket_url": ""
  },
  {
    "id": "20250521-F325-001",
    "title": "Test Event 3",
    "description": "New event 3",
    "long_description": "New Test Event 3",
    "event_date": "2025-05-21",
    "display_from_date": "2025-05-20",
    "tags": [
      "sonar",
      "test",
      "you",
      "me"
    ],
    "full_image_url": "https://sonar-media.sfo3.digitaloceanspaces.com/images/20250521-F325-001-full.png",
    "small_image_url": "https://sonar-media.sfo3.digitaloceanspaces.com/images/20250521-F325-001-small.png",
    "thumb_image_url": "https://sonar-media.sfo3.digitaloceanspaces.com/images/20250521-F325-001-thumb.png",
    "group_id": "g1",
    "images_uploaded_to_s3": true,
    "event_updated_not_submitted": false,
    "ticket_url": ""
  },
  {
    "id": "20250519-F325-002",
    "title": "New Title",
    "description": "new Description",
    "long_description": "here's a longer description",
    "event_date": "2025-05-23",
    "display_from_date": "2025-05-20",
    "tags": [
      "sonar",
      "beefy",
      "bigone"
    ],
    "full_image_url": "https://sonar-media.sfo3.digitaloceanspaces.com/images/20250519-F325-002-full.png",
    "small_image_url": "https://sonar-media.sfo3.digitaloceanspaces.com/images/20250519-F325-002-small.png",
    "thumb_image_url": "https://sonar-media.sfo3.digitaloceanspaces.com/images/20250519-F325-002-thumb.png",
    "group_id": "g1",
    "images_uploaded_to_s3": true,
    "event_updated_not_submitted": false,
    "ticket_url": ""
  },
  {
    "id": "20250519-F325-003",
    "title": "New event Trois",
    "description": "New Event Here People",
    "long_description": "Here's a new event",
    "event_date": "2025-05-23",
    "display_from_date": "2025-05-19",
    "tags": [
      "sonar",
      "test",
      "me",
      "you"
    ],
    "ticket_url": "https://example.com/tickets",
    "full_image_url": "https://sonar-media.sfo3.digitaloceanspaces.com/images/20250519-F325-003-full.png",
    "small_image_url": "https://sonar-media.sfo3.digitaloceanspaces.com/images/20250519-F325-003-small.png",
    "thumb_image_url": "https://sonar-media.sfo3.digitaloceanspaces.com/images/20250519-F325-003-thumb.png",
    "group_id": "g1",
    "images_uploaded_to_s3": true,
    "event_updated_not_submitted": false
  },
  {
    "id": "20250519-F325-005",
    "title": "Beginning Dance - Level 1",
    "description": "Beginning Dance, easy on the brain, and on the body",
    "long_description": "Beginning Dance level 1 is for people starting again, looking to get some activity and find a new community. ",
    "event_date": "2025-10-06T10:00",
    "display_from_date": "2025-10-02",
    "tags": [
      "academy",
      "dance",
      "beginner"
    ],
    "ticket_url": "",
    "full_image_url": "https://sonar-media.sfo3.cdn.digitaloceanspaces.com/images/zzz-dance-seated-couple-full.png",
    "small_image_url": "https://sonar-media.sfo3.cdn.digitaloceanspaces.com/images/zzz-dance-seated-couple-small.png",
    "thumb_image_url": "https://sonar-media.sfo3.cdn.digitaloceanspaces.com/images/zzz-dance-seated-couple-thumb.png",
    "group_id": "g1",
    "images_uploaded_to_s3": true,
    "event_updated_not_submitted": false
  },
  {
    "id": "20251003-DFC4-001",
    "title": "Beginning Dance - Level 1",
    "description": "Beginning Dance, easy on the brain, and on the body",
    "long_description": "Beginning Dance level 1 is for people starting again, looking to get some activity and find a new community. ",
    "event_date": "2025-10-08T10:00",
    "display_from_date": "2025-10-02",
    "tags": [
      "academy",
      "dance",
      "beginner"
    ],
    "ticket_url": "",
    "full_image_url": "https://sonar-media.sfo3.cdn.digitaloceanspaces.com/images/zzz-dance-seated-couple-full.png",
    "small_image_url": "https://sonar-media.sfo3.cdn.digitaloceanspaces.com/images/zzz-dance-seated-couple-small.png",
    "thumb_image_url": "https://sonar-media.sfo3.cdn.digitaloceanspaces.com/images/zzz-dance-seated-couple-thumb.png",
    "group_id": "g1",
    "images_uploaded_to_s3": true,
    "event_updated_not_submitted": false
  },
  {
    "id": "20251003-DFC4-002",
    "title": "Beginning Dance - Level 1",
    "description": "Beginning Dance, easy on the brain, and on the body",
    "long_description": "Beginning Dance level 1 is for people starting again, looking to get some activity and find a new community. ",
    "event_date": "2025-10-10T10:00",
    "display_from_date": "2025-10-02",
    "tags": [
      "academy",
      "dance",
      "beginner"
    ],
    "ticket_url": "",
    "full_image_url": "https://sonar-media.sfo3.cdn.digitaloceanspaces.com/images/zzz-dance-seated-couple-full.png",
    "small_image_url": "https://sonar-media.sfo3.cdn.digitaloceanspaces.com/images/zzz-dance-seated-couple-small.png",
    "thumb_image_url": "https://sonar-media.sfo3.cdn.digitaloceanspaces.com/images/zzz-dance-seated-couple-thumb.png",
    "group_id": "g1",
    "images_uploaded_to_s3": true,
    "event_updated_not_submitted": false
  }
]